setup.py
sas_sample_app/__init__.py
sas_sample_app.egg-info/PKG-INFO
sas_sample_app.egg-info/SOURCES.txt
sas_sample_app.egg-info/dependency_links.txt
sas_sample_app.egg-info/requires.txt
sas_sample_app.egg-info/top_level.txt
sas_sample_app/package_one/__init__.py
sas_sample_app/package_one/train_Data_Transform.py