Metadata-Version: 1.0
Name: sas-sample-app
Version: 1.1.4
Summary: step 1 Tutorial
Home-page: UNKNOWN
Author: Viswanathan Muthiah
Author-email: viswanathan.m1@tcs.com
License: MIT
Platform: UNKNOWN
